jupyter_conf_search/__init__.py
jupyter_conf_search/__main__.py
jupyter_conf_search/jupyter_conf_search.py
jupyter_conf_search-0.4.4.dist-info/entry_points.txt
jupyter_conf_search-0.4.4.dist-info/WHEEL
jupyter_conf_search-0.4.4.dist-info/METADATA
jupyter_conf_search-0.4.4.dist-info/RECORD
