Metadata-Version: 1.2
Name: jupyter_conf_search
Version: 0.4.4
Summary: Utility for searching through jupyter configuration files, using jupyter's path definitions to find their locations dynamically.
Home-page: https://michaelpacer.com
License: UNKNOWN
Author: michaelpacer
Author-email: mpacer@berkeley.edu
Requires-Python: >3
Classifier: License :: OSI Approved :: MIT License
